odoo/addons/ssi_employee_external_assignment/README.rst
odoo/addons/ssi_employee_external_assignment/__init__.py
odoo/addons/ssi_employee_external_assignment/__manifest__.py
odoo/addons/ssi_employee_external_assignment/approval_template/employee_external_assignment.xml
odoo/addons/ssi_employee_external_assignment/i18n/ssi_employee_external_assignment.pot
odoo/addons/ssi_employee_external_assignment/ir_sequence/employee_external_assignment.xml
odoo/addons/ssi_employee_external_assignment/models/__init__.py
odoo/addons/ssi_employee_external_assignment/models/employee_external_assignment.py
odoo/addons/ssi_employee_external_assignment/models/employee_external_assignment_type.py
odoo/addons/ssi_employee_external_assignment/models/hr_employee.py
odoo/addons/ssi_employee_external_assignment/policy_template/employee_external_assignment.xml
odoo/addons/ssi_employee_external_assignment/security/ir_model_access/employee_external_assignment.xml
odoo/addons/ssi_employee_external_assignment/security/ir_model_access/employee_external_assignment_type.xml
odoo/addons/ssi_employee_external_assignment/security/ir_module_category/employee_external_assignment_module_category.xml
odoo/addons/ssi_employee_external_assignment/security/ir_rule/employee_external_assignment.xml
odoo/addons/ssi_employee_external_assignment/security/res_groups/employee_external_assignment.xml
odoo/addons/ssi_employee_external_assignment/security/res_groups/employee_external_assignment_type.xml
odoo/addons/ssi_employee_external_assignment/sequence_template/employee_external_assignment.xml
odoo/addons/ssi_employee_external_assignment/static/description/icon.png
odoo/addons/ssi_employee_external_assignment/views/employee_external_assignment_type_views.xml
odoo/addons/ssi_employee_external_assignment/views/employee_external_assignment_views.xml
odoo/addons/ssi_employee_external_assignment/views/hr_employee.xml
odoo14_addon_ssi_employee_external_assignment-14.0.1.0.1.dev3.dist-info/METADATA
odoo14_addon_ssi_employee_external_assignment-14.0.1.0.1.dev3.dist-info/WHEEL
odoo14_addon_ssi_employee_external_assignment-14.0.1.0.1.dev3.dist-info/top_level.txt
odoo14_addon_ssi_employee_external_assignment-14.0.1.0.1.dev3.dist-info/RECORD
