Metadata-Version: 2.1
Name: odoo14-addon-ssi_employee_external_assignment
Version: 14.0.1.0.1.dev3
Summary: Employee External Assignment
Home-page: https://github.com/open-synergy/employee-external-assignment
Author: OpenSynergy Indonesia, PT. Simetri Sinergi Indonesia
License: AGPL-3
Classifier: Programming Language :: Python
Classifier: Framework :: Odoo
Classifier: Framework :: Odoo :: 14.0
Classifier: License :: OSI Approved :: GNU Affero General Public License v3
Requires-Python: >=3.6
Requires-Dist: odoo14-addon-ssi-employee-document-mixin
Requires-Dist: odoo14-addon-ssi-master-data-mixin
Requires-Dist: odoo14-addon-ssi-transaction-cancel-mixin
Requires-Dist: odoo14-addon-ssi-transaction-confirm-mixin
Requires-Dist: odoo14-addon-ssi-transaction-date-duration-mixin
Requires-Dist: odoo14-addon-ssi-transaction-done-mixin
Requires-Dist: odoo14-addon-ssi-transaction-open-mixin
Requires-Dist: odoo14-addon-ssi-transaction-terminate-mixin
Requires-Dist: odoo<14.1dev,>=14.0a
